v/__init__.py
v/colour.py
v/file.py
v/game.py
v/maths.py
v-3.4.0.dist-info/LICENSE
v-3.4.0.dist-info/METADATA
v-3.4.0.dist-info/WHEEL
v-3.4.0.dist-info/top_level.txt
v-3.4.0.dist-info/RECORD
