Metadata-Version: 2.1
Name: v
Version: 3.4.0
Summary: v: the ultimate package for everything
Author-email: Dylan Rogers <opendylan@proton.me>
Project-URL: Homepage, http://123web.uk/v/py
Project-URL: Bug Tracker, http://123web.uk/v/py/bugs
Classifier: Programming Language :: Python
Classifier: License :: OSI Approved :: MIT License
Classifier: Operating System :: OS Independent
Requires-Python: >=2.0
License-File: LICENSE
